streamsad/__init__.py
streamsad/config.py
streamsad/feature_extractor.py
streamsad/sad.py
streamsad/models/model_2025-06-10.onnx
streamsad-0.1.4.dist-info/licenses/LICENSE
streamsad-0.1.4.dist-info/METADATA
streamsad-0.1.4.dist-info/WHEEL
streamsad-0.1.4.dist-info/top_level.txt
streamsad-0.1.4.dist-info/RECORD
