Metadata-Version: 2.4
Name: streamsad
Version: 0.1.4
Summary: A light-weight, streaming speech activity detection (SAD) module, designed for real-time speech-only classification
Author-email: Mohammad Hassan Sohan Ajini <mohamad.hasan.sohan.ajini@gmail.com>
License-Expression: MIT
Project-URL: Homepage, https://github.com/mohamad-hasan-sohan-ajini/streamsad
Project-URL: Repository, https://github.com/mohamad-hasan-sohan-ajini/streamsad
Project-URL: Issues, https://github.com/mohamad-hasan-sohan-ajini/streamsad/issues
Classifier: Intended Audience :: Developers
Classifier: Intended Audience :: Science/Research
Classifier: Programming Language :: Python :: 3.10
Classifier: Programming Language :: Python :: 3.11
Classifier: Programming Language :: Python :: 3.12
Classifier: Programming Language :: Python :: 3.13
Classifier: Topic :: Scientific/Engineering :: Artificial Intelligence
Classifier: Topic :: Multimedia :: Sound/Audio
Classifier: Topic :: Multimedia :: Sound/Audio :: Analysis
Classifier: Topic :: Multimedia :: Sound/Audio :: Speech
Requires-Python: >=3.10
License-File: LICENSE
Requires-Dist: numpy==1.26.3
Requires-Dist: onnxruntime==1.20.1
Provides-Extra: test
Requires-Dist: pytest; extra == "test"
Requires-Dist: soundfile; extra == "test"
Dynamic: license-file
